molgri/__init__.py
molgri/constants.py
molgri/examples/.H2O_H2O_o_ico_500_b_ico_5_t_3830884671.xtc_offsets.lock
molgri/examples/.H2O_H2O_o_ico_500_b_ico_5_t_3830884671.xtc_offsets.npz
molgri/examples/CL.gro
molgri/examples/Cube3D_1538.npy
molgri/examples/Cube4D_16448.npy
molgri/examples/Cube4D_2080.npy
molgri/examples/H2O.gro
molgri/examples/H2O_H2O.top
molgri/examples/H2O_H2O_o_ico_500_b_ico_5_t_3830884671.gro
molgri/examples/H2O_H2O_o_ico_500_b_ico_5_t_3830884671.xtc
molgri/examples/H2O_H2O_o_ico_500_b_ico_5_t_3830884671.xvg
molgri/examples/Icosahedron_2562.npy
molgri/examples/NA.gro
molgri/examples/NH3.gro
molgri/examples/default_configuration_file.yaml
molgri/examples/example_pdb.pdb
molgri/examples/example_protein.gro
molgri/examples/ffbonded.itp
molgri/examples/ffnonbonded.itp
molgri/examples/glucose.xyz
molgri/examples/he_forcefield.itp
molgri/examples/index_first_mol.ndx
molgri/examples/mdrun.mdp
molgri/examples/nvt_he.gro
molgri/examples/select_2
molgri/examples/select_3_and_0
molgri/examples/select_energy_five
molgri/examples/select_group_zero
molgri/examples/topol_he.top
molgri/io.py
molgri/molecules/__init__.py
molgri/molecules/pts.py
molgri/molecules/rate_merger.py
molgri/molecules/transitions.py
molgri/naming.py
molgri/paths.py
molgri/plotting/__init__.py
molgri/plotting/abstract.py
molgri/plotting/create_vmdlog.py
molgri/plotting/fullgrid_plots.py
molgri/plotting/other_plots.py
molgri/plotting/spheregrid_plots.py
molgri/plotting/transition_plots.py
molgri/plotting/widgets.py
molgri/scripts/generate_grid.py
molgri/scripts/generate_pt.py
molgri/scripts/set_up_io.py
molgri/scripts/vmd_position_msm_water_he
molgri/scripts/vmd_position_msm_water_vacuum
molgri/scripts/vmd_position_sqra_water
molgri/space/__init__.py
molgri/space/fullgrid.py
molgri/space/polytopes.py
molgri/space/rotations.py
molgri/space/rotobj.py
molgri/space/translations.py
molgri/space/utils.py
molgri/space/voronoi.py
molgri/wrappers.py
molgri-2.0.0.dist-info/LICENSE
molgri-2.0.0.dist-info/METADATA
molgri-2.0.0.dist-info/WHEEL
molgri-2.0.0.dist-info/entry_points.txt
molgri-2.0.0.dist-info/RECORD
