Metadata-Version: 2.1
Name: molgri
Version: 2.0.0
Summary: Systematically generate structures of two molecules based on discretisation of translational and rotational space.
Home-page: https://www.bcp.fu-berlin.de/en/chemie/chemie/forschung/PhysTheoChem/agkeller/index.html
License: LICENSE
Keywords: pseudotrajectory,molecular grids,association,state space discretisation
Author: Hana Zupan
Author-email: hana.zupan@fu-berlin.de
Requires-Python: >=3.11,<3.13
Classifier: License :: Other/Proprietary License
Classifier: Programming Language :: Python :: 3
Classifier: Programming Language :: Python :: 3.11
Classifier: Programming Language :: Python :: 3.12
Requires-Dist: kaleido (==0.2.1)
Requires-Dist: matplotlib (>=3.9.2,<4.0.0)
Requires-Dist: mdanalysis (>=2.7.0,<3.0.0)
Requires-Dist: networkx (>=3.4.2,<4.0.0)
Requires-Dist: numpy (>=1.22.3,<2.0)
Requires-Dist: pandas (>=2.2.3,<3.0.0)
Requires-Dist: plotly (==5.3.1)
Requires-Dist: scipy (>=1.14.1,<2.0.0)
Requires-Dist: seaborn (>=0.13.2,<0.14.0)
Requires-Dist: tqdm (>=4.66.5,<5.0.0)
Project-URL: Documentation, https://molgri.readthedocs.io/en/main/
Project-URL: Repository, https://github.com/bkellerlab/molecularRotationalGrids
